vcorelib/__init__.py
vcorelib/dev_requirements.txt
vcorelib/names.py
vcorelib/py.typed
vcorelib/python.py
vcorelib/requirements.txt
vcorelib/args/__init__.py
vcorelib/args/newline.py
vcorelib/asyncio/__init__.py
vcorelib/asyncio/cli.py
vcorelib/asyncio/poll.py
vcorelib/asyncio/subprocess.py
vcorelib/data/md/default.md
vcorelib/dict/__init__.py
vcorelib/dict/cache.py
vcorelib/dict/codec.py
vcorelib/dict/config.py
vcorelib/dict/env.py
vcorelib/graph/__init__.py
vcorelib/graph/abc.py
vcorelib/graph/edge.py
vcorelib/graph/node.py
vcorelib/graph/port.py
vcorelib/io/__init__.py
vcorelib/io/abc.py
vcorelib/io/cache.py
vcorelib/io/decode.py
vcorelib/io/encode.py
vcorelib/io/fifo.py
vcorelib/io/file_writer.py
vcorelib/io/mapping.py
vcorelib/io/markdown.py
vcorelib/io/types.py
vcorelib/io/arbiter/__init__.py
vcorelib/io/arbiter/base.py
vcorelib/io/arbiter/context.py
vcorelib/io/arbiter/directory.py
vcorelib/io/archive/__init__.py
vcorelib/io/bus/__init__.py
vcorelib/logging/__init__.py
vcorelib/logging/args.py
vcorelib/logging/list.py
vcorelib/logging/time.py
vcorelib/math/__init__.py
vcorelib/math/constants.py
vcorelib/math/keeper.py
vcorelib/math/time.py
vcorelib/math/unit.py
vcorelib/math/analysis/__init__.py
vcorelib/math/analysis/average.py
vcorelib/math/analysis/buffer.py
vcorelib/math/analysis/weighted.py
vcorelib/math/analysis/rate/__init__.py
vcorelib/math/analysis/rate/limiter.py
vcorelib/namespace/__init__.py
vcorelib/namespace/base.py
vcorelib/namespace/mixin.py
vcorelib/paths/__init__.py
vcorelib/paths/base.py
vcorelib/paths/context.py
vcorelib/paths/find.py
vcorelib/paths/hashing.py
vcorelib/paths/info.py
vcorelib/paths/info_cache.py
vcorelib/platform/__init__.py
vcorelib/schemas/__init__.py
vcorelib/schemas/base.py
vcorelib/schemas/json.py
vcorelib/schemas/mixins.py
vcorelib/script/__init__.py
vcorelib/target/__init__.py
vcorelib/target/evaluation.py
vcorelib/target/expression.py
vcorelib/target/resolver.py
vcorelib/task/__init__.py
vcorelib/task/manager.py
vcorelib-3.6.7.dist-info/licenses/LICENSE
vcorelib-3.6.7.dist-info/METADATA
vcorelib-3.6.7.dist-info/WHEEL
vcorelib-3.6.7.dist-info/top_level.txt
vcorelib-3.6.7.dist-info/RECORD
